docs/source/conf.py
yomix/VERSION
yomix/__init__.py
yomix/__main__.py
yomix/assets/arrow.png
yomix/assets/arrow_pressed.png
yomix/assets/helvetica.ttf
yomix/assets/lasso_select_modes.png
yomix/assets/yomix_logo.png
yomix/assets/yomix_logo_big.png
yomix/example/pbmc.h5ad
yomix/plotting/__init__.py
yomix/plotting/features.py
yomix/plotting/figure.py
yomix/plotting/legend.py
yomix/server/__init__.py
yomix/server/server.py
yomix/tools/__init__.py
yomix/tools/arrow.py
yomix/tools/download.py
yomix/tools/gene_query.py
yomix/tools/signatures.py
yomix/tools/subsets.py
yomix-1.6.0.dist-info/licenses/LICENSE
yomix-1.6.0.dist-info/METADATA
yomix-1.6.0.dist-info/WHEEL
yomix-1.6.0.dist-info/entry_points.txt
yomix-1.6.0.dist-info/top_level.txt
yomix-1.6.0.dist-info/RECORD
