Metadata-Version: 2.4
Name: yomix
Version: 1.6.0
Summary: yomix: an interactive tool to explore low dimensional embeddings of omics data
Home-page: https://github.com/perrin-isir/yomix
License: BSD 3-Clause License
Requires-Python: >=3.11
License-File: LICENSE
Requires-Dist: pandas>=2.2.2
Requires-Dist: numpy>=1.26.0
Requires-Dist: matplotlib>=3.8.0
Requires-Dist: bokeh<3.7,>=3.4.1
Requires-Dist: anndata>=0.10.7
Requires-Dist: scipy>=1.13.1
Requires-Dist: requests>=2.32.3
Requires-Dist: nest-asyncio>=1.6.0
Dynamic: home-page
Dynamic: license-file
Dynamic: summary
